autorag/__init__.py
autorag/cli.py
autorag/database/__init__.py
autorag/database/mongodb.py
autorag/database/postgres.py
autorag/database/supabase.py
autorag/evaluation/__init__.py
autorag/evaluation/base_evaluator.py
autorag/evaluation/custom_eval.py
autorag/evaluation/evaluator_factory.py
autorag/evaluation/ragas_eval.py
autorag/optimization/__init__.py
autorag/optimization/bayesian.py
autorag/optimization/grid_search.py
autorag/rag/__init__.py
autorag/rag/chroma_store.py
autorag/rag/embeddings.py
autorag/rag/llm_client.py
autorag/rag/pipeline.py
autorag/synthetic/__init__.py
autorag/synthetic/generator.py
autorag/tasks/__init__.py
autorag/tasks/celery_app.py
autorag/tasks/optimization_task.py
autorag/tasks/progress.py
autorag/utils/__init__.py
autorag/utils/config.py
autorag/utils/text_utils.py
autorag_optim-0.1.3.dist-info/METADATA
autorag_optim-0.1.3.dist-info/WHEEL
autorag_optim-0.1.3.dist-info/entry_points.txt
autorag_optim-0.1.3.dist-info/licenses/LICENSE
autorag_optim-0.1.3.dist-info/RECORD
