Metadata-Version: 2.4
Name: autorag-optim
Version: 0.1.3
Summary: A CLI tool that automates RAG hyperparameter optimization using Bayesian search and synthetic data generation
Project-URL: Homepage, https://github.com/vatsalpjain/autorag-optim
Project-URL: Repository, https://github.com/vatsalpjain/autorag-optim.git
Project-URL: Bug Tracker, https://github.com/vatsalpjain/autorag-optim/issues
Author-email: Vatsal Jain <vatsalpjain@gmail.com>
License-Expression: MIT
License-File: LICENSE
Keywords: ai,bayesian,chromadb,cli,langchain,llm,optimization,rag,retrieval
Classifier: Development Status :: 3 - Alpha
Classifier: Environment :: Console
Classifier: Intended Audience :: Developers
Classifier: License :: OSI Approved :: MIT License
Classifier: Programming Language :: Python :: 3
Classifier: Programming Language :: Python :: 3.10
Classifier: Programming Language :: Python :: 3.11
Classifier: Programming Language :: Python :: 3.12
Classifier: Programming Language :: Python :: 3.13
Classifier: Topic :: Scientific/Engineering :: Artificial Intelligence
Classifier: Topic :: Software Development :: Libraries :: Python Modules
Requires-Python: >=3.10
Requires-Dist: celery>=5.6.0
Requires-Dist: chromadb>=0.4.0
Requires-Dist: groq>=1.0.0
Requires-Dist: httpx>=0.28.1
Requires-Dist: langchain-community>=0.4.1
Requires-Dist: langchain-huggingface>=1.2.0
Requires-Dist: langchain>=1.2.0
Requires-Dist: optuna>=4.6.0
Requires-Dist: pi169>=0.1
Requires-Dist: psycopg2-binary>=2.9.11
Requires-Dist: pydantic-settings>=2.12.0
Requires-Dist: pydantic>=2.12.5
Requires-Dist: pymongo>=4.15.5
Requires-Dist: python-dotenv>=1.2.1
Requires-Dist: pyyaml>=6.0.3
Requires-Dist: redis>=7.1.0
Requires-Dist: rich>=14.2.0
Requires-Dist: sentence-transformers>=3.3.1
Requires-Dist: supabase>=2.27.0
Requires-Dist: tenacity>=9.1.2
Requires-Dist: tiktoken>=0.12.0
Requires-Dist: torch>=2.5.1
Requires-Dist: typer>=0.20.1
Provides-Extra: dev
Requires-Dist: build>=1.3.0; extra == 'dev'
Requires-Dist: hatchling>=1.28.0; extra == 'dev'
Requires-Dist: pytest-asyncio>=1.3.0; extra == 'dev'
Requires-Dist: pytest-cov>=4.1.0; extra == 'dev'
Requires-Dist: pytest>=9.0.2; extra == 'dev'
Requires-Dist: twine>=6.2.0; extra == 'dev'
Requires-Dist: wheel>=0.45.1; extra == 'dev'
Provides-Extra: ragas
Requires-Dist: ragas>=0.2.0; extra == 'ragas'
